finer.py
finer-0.1.0.dist-info/LICENSE
finer-0.1.0.dist-info/WHEEL
finer-0.1.0.dist-info/METADATA
finer-0.1.0.dist-info/RECORD
