Metadata-Version: 2.1
Name: finer
Version: 0.1.0
Summary: 
Author: caiozim112
Author-email: caioopua@gmail.com
Requires-Python: >=3.10,<3.12
Classifier: Programming Language :: Python :: 3
Classifier: Programming Language :: Python :: 3.10
Requires-Dist: click (>=8.1.3,<9.0.0)
Requires-Dist: datasets (==2.1.0)
Requires-Dist: gensim (==4.2.0)
Requires-Dist: protobuf (==3.20.3)
Requires-Dist: regex (>=2023.6.3,<2024.0.0)
Requires-Dist: scikit-learn (>=1.0.2)
Requires-Dist: seqeval (==1.2.2)
Requires-Dist: tensorflow (==2.8.0)
Requires-Dist: tensorflow-addons (==0.16.1)
Requires-Dist: tf2crf (==0.1.24)
Requires-Dist: tokenizers (==0.12.1)
Requires-Dist: tqdm (>=4.65.0,<5.0.0)
Requires-Dist: transformers (==4.18.0)
Requires-Dist: wandb (==0.12.16)
Requires-Dist: wget (>=3.2,<4.0)
